{
	"configurations" : 
	[
		{
			"directories" : 
			[
				{
					"build" : ".",
					"childIndexes" : 
					[
						1,
						2,
						3,
						4,
						5
					],
					"hasInstallRule" : true,
					"jsonFile" : "directory-.-Release-7893c4f765cb1eb3849c.json",
					"minimumCMakeVersion" : 
					{
						"string" : "3.12"
					},
					"projectIndex" : 0,
					"source" : ".",
					"targetIndexes" : 
					[
						12,
						19
					]
				},
				{
					"build" : "rviz_plugin_render_tools",
					"hasInstallRule" : true,
					"jsonFile" : "directory-rviz_plugin_render_tools-Release-ed7fbc9f2a30e68a893a.json",
					"minimumCMakeVersion" : 
					{
						"string" : "3.12"
					},
					"parentIndex" : 0,
					"projectIndex" : 0,
					"source" : "rviz_plugin_render_tools",
					"targetIndexes" : 
					[
						13,
						14
					]
				},
				{
					"build" : "robot_state_rviz_plugin",
					"hasInstallRule" : true,
					"jsonFile" : "directory-robot_state_rviz_plugin-Release-5f75891e8cd150b324a2.json",
					"minimumCMakeVersion" : 
					{
						"string" : "3.12"
					},
					"parentIndex" : 0,
					"projectIndex" : 0,
					"source" : "robot_state_rviz_plugin",
					"targetIndexes" : 
					[
						8,
						9,
						10,
						11
					]
				},
				{
					"build" : "planning_scene_rviz_plugin",
					"hasInstallRule" : true,
					"jsonFile" : "directory-planning_scene_rviz_plugin-Release-b0dfdab8a32411bbd63a.json",
					"minimumCMakeVersion" : 
					{
						"string" : "3.12"
					},
					"parentIndex" : 0,
					"projectIndex" : 0,
					"source" : "planning_scene_rviz_plugin",
					"targetIndexes" : 
					[
						4,
						5,
						6,
						7
					]
				},
				{
					"build" : "motion_planning_rviz_plugin",
					"hasInstallRule" : true,
					"jsonFile" : "directory-motion_planning_rviz_plugin-Release-c1c480d7a46ee07ff19c.json",
					"minimumCMakeVersion" : 
					{
						"string" : "3.12"
					},
					"parentIndex" : 0,
					"projectIndex" : 0,
					"source" : "motion_planning_rviz_plugin",
					"targetIndexes" : 
					[
						0,
						1,
						2,
						3
					]
				},
				{
					"build" : "trajectory_rviz_plugin",
					"hasInstallRule" : true,
					"jsonFile" : "directory-trajectory_rviz_plugin-Release-1b3a25f294a9327a8e29.json",
					"minimumCMakeVersion" : 
					{
						"string" : "3.12"
					},
					"parentIndex" : 0,
					"projectIndex" : 0,
					"source" : "trajectory_rviz_plugin",
					"targetIndexes" : 
					[
						15,
						16,
						17,
						18
					]
				}
			],
			"name" : "Release",
			"projects" : 
			[
				{
					"directoryIndexes" : 
					[
						0,
						1,
						2,
						3,
						4,
						5
					],
					"name" : "moveit_ros_visualization",
					"targetIndexes" : 
					[
						0,
						1,
						2,
						3,
						4,
						5,
						6,
						7,
						8,
						9,
						10,
						11,
						12,
						13,
						14,
						15,
						16,
						17,
						18,
						19
					]
				}
			],
			"targets" : 
			[
				{
					"directoryIndex" : 4,
					"id" : "moveit_motion_planning_rviz_plugin::@52165aa309b6597994f1",
					"jsonFile" : "target-moveit_motion_planning_rviz_plugin-Release-b006f3719471a1208a15.json",
					"name" : "moveit_motion_planning_rviz_plugin",
					"projectIndex" : 0
				},
				{
					"directoryIndex" : 4,
					"id" : "moveit_motion_planning_rviz_plugin_autogen::@52165aa309b6597994f1",
					"jsonFile" : "target-moveit_motion_planning_rviz_plugin_autogen-Release-651f54b31fb9ded82030.json",
					"name" : "moveit_motion_planning_rviz_plugin_autogen",
					"projectIndex" : 0
				},
				{
					"directoryIndex" : 4,
					"id" : "moveit_motion_planning_rviz_plugin_core::@52165aa309b6597994f1",
					"jsonFile" : "target-moveit_motion_planning_rviz_plugin_core-Release-ec255c7447d88623197d.json",
					"name" : "moveit_motion_planning_rviz_plugin_core",
					"projectIndex" : 0
				},
				{
					"directoryIndex" : 4,
					"id" : "moveit_motion_planning_rviz_plugin_core_autogen::@52165aa309b6597994f1",
					"jsonFile" : "target-moveit_motion_planning_rviz_plugin_core_autogen-Release-4c1f2471f8b4e72cd834.json",
					"name" : "moveit_motion_planning_rviz_plugin_core_autogen",
					"projectIndex" : 0
				},
				{
					"directoryIndex" : 3,
					"id" : "moveit_planning_scene_rviz_plugin::@0526de66a6d4fe5c596d",
					"jsonFile" : "target-moveit_planning_scene_rviz_plugin-Release-b59bd6328649176cc565.json",
					"name" : "moveit_planning_scene_rviz_plugin",
					"projectIndex" : 0
				},
				{
					"directoryIndex" : 3,
					"id" : "moveit_planning_scene_rviz_plugin_autogen::@0526de66a6d4fe5c596d",
					"jsonFile" : "target-moveit_planning_scene_rviz_plugin_autogen-Release-a950baddb0ad721edc6f.json",
					"name" : "moveit_planning_scene_rviz_plugin_autogen",
					"projectIndex" : 0
				},
				{
					"directoryIndex" : 3,
					"id" : "moveit_planning_scene_rviz_plugin_core::@0526de66a6d4fe5c596d",
					"jsonFile" : "target-moveit_planning_scene_rviz_plugin_core-Release-52ec5ff9e87ddabde0f9.json",
					"name" : "moveit_planning_scene_rviz_plugin_core",
					"projectIndex" : 0
				},
				{
					"directoryIndex" : 3,
					"id" : "moveit_planning_scene_rviz_plugin_core_autogen::@0526de66a6d4fe5c596d",
					"jsonFile" : "target-moveit_planning_scene_rviz_plugin_core_autogen-Release-0a4beb99df9431ae5c73.json",
					"name" : "moveit_planning_scene_rviz_plugin_core_autogen",
					"projectIndex" : 0
				},
				{
					"directoryIndex" : 2,
					"id" : "moveit_robot_state_rviz_plugin::@3cccd1ee7f0cc842f242",
					"jsonFile" : "target-moveit_robot_state_rviz_plugin-Release-84172a8c5987ef5c9e3b.json",
					"name" : "moveit_robot_state_rviz_plugin",
					"projectIndex" : 0
				},
				{
					"directoryIndex" : 2,
					"id" : "moveit_robot_state_rviz_plugin_autogen::@3cccd1ee7f0cc842f242",
					"jsonFile" : "target-moveit_robot_state_rviz_plugin_autogen-Release-c5e63af22a9d909b35d0.json",
					"name" : "moveit_robot_state_rviz_plugin_autogen",
					"projectIndex" : 0
				},
				{
					"directoryIndex" : 2,
					"id" : "moveit_robot_state_rviz_plugin_core::@3cccd1ee7f0cc842f242",
					"jsonFile" : "target-moveit_robot_state_rviz_plugin_core-Release-4b5234431109cf12d122.json",
					"name" : "moveit_robot_state_rviz_plugin_core",
					"projectIndex" : 0
				},
				{
					"directoryIndex" : 2,
					"id" : "moveit_robot_state_rviz_plugin_core_autogen::@3cccd1ee7f0cc842f242",
					"jsonFile" : "target-moveit_robot_state_rviz_plugin_core_autogen-Release-88326a12e88f41acaf4c.json",
					"name" : "moveit_robot_state_rviz_plugin_core_autogen",
					"projectIndex" : 0
				},
				{
					"directoryIndex" : 0,
					"id" : "moveit_ros_visualization_uninstall::@6890427a1f51a3e7e1df",
					"jsonFile" : "target-moveit_ros_visualization_uninstall-Release-dfca29822ad44276a346.json",
					"name" : "moveit_ros_visualization_uninstall",
					"projectIndex" : 0
				},
				{
					"directoryIndex" : 1,
					"id" : "moveit_rviz_plugin_render_tools::@11af576cd519c4ccae31",
					"jsonFile" : "target-moveit_rviz_plugin_render_tools-Release-7a6064436b2078ea99cc.json",
					"name" : "moveit_rviz_plugin_render_tools",
					"projectIndex" : 0
				},
				{
					"directoryIndex" : 1,
					"id" : "moveit_rviz_plugin_render_tools_autogen::@11af576cd519c4ccae31",
					"jsonFile" : "target-moveit_rviz_plugin_render_tools_autogen-Release-81d19372c6b294fcf75a.json",
					"name" : "moveit_rviz_plugin_render_tools_autogen",
					"projectIndex" : 0
				},
				{
					"directoryIndex" : 5,
					"id" : "moveit_trajectory_rviz_plugin::@ea9655eb8b0ab182c77d",
					"jsonFile" : "target-moveit_trajectory_rviz_plugin-Release-70976bf60bbb4d3c865b.json",
					"name" : "moveit_trajectory_rviz_plugin",
					"projectIndex" : 0
				},
				{
					"directoryIndex" : 5,
					"id" : "moveit_trajectory_rviz_plugin_autogen::@ea9655eb8b0ab182c77d",
					"jsonFile" : "target-moveit_trajectory_rviz_plugin_autogen-Release-222261dd976245f197d9.json",
					"name" : "moveit_trajectory_rviz_plugin_autogen",
					"projectIndex" : 0
				},
				{
					"directoryIndex" : 5,
					"id" : "moveit_trajectory_rviz_plugin_core::@ea9655eb8b0ab182c77d",
					"jsonFile" : "target-moveit_trajectory_rviz_plugin_core-Release-57da3b1aad10ee71a469.json",
					"name" : "moveit_trajectory_rviz_plugin_core",
					"projectIndex" : 0
				},
				{
					"directoryIndex" : 5,
					"id" : "moveit_trajectory_rviz_plugin_core_autogen::@ea9655eb8b0ab182c77d",
					"jsonFile" : "target-moveit_trajectory_rviz_plugin_core_autogen-Release-ef1f5694582b7dac7501.json",
					"name" : "moveit_trajectory_rviz_plugin_core_autogen",
					"projectIndex" : 0
				},
				{
					"directoryIndex" : 0,
					"id" : "uninstall::@6890427a1f51a3e7e1df",
					"jsonFile" : "target-uninstall-Release-04bff85fc8c0949743ba.json",
					"name" : "uninstall",
					"projectIndex" : 0
				}
			]
		}
	],
	"kind" : "codemodel",
	"paths" : 
	{
		"build" : "/home/kaushal/kaushal/moveit_ws/build/moveit_ros_visualization",
		"source" : "/home/kaushal/kaushal/moveit_ws/src/moveit2/moveit_ros/visualization"
	},
	"version" : 
	{
		"major" : 2,
		"minor" : 3
	}
}
